torrent_tracker_scraper/__init__.py
torrent_tracker_scraper/example.py
torrent_tracker_scraper/scraper.py
torrent_tracker_scraper-4.1.0.dist-info/LICENSE
torrent_tracker_scraper-4.1.0.dist-info/METADATA
torrent_tracker_scraper-4.1.0.dist-info/WHEEL
torrent_tracker_scraper-4.1.0.dist-info/top_level.txt
torrent_tracker_scraper-4.1.0.dist-info/RECORD
