Metadata-Version: 2.1
Name: torrent-tracker-scraper
Version: 4.1.0
Summary: A UDP torrent tracker scraper written in Python 3
Home-page: https://github.com/49e94b8f256530dc0d41f740dfe8a4c1/torrent-tracker-scraper
Author: ziggs
Author-email: kenokech94@gmail.com
License: UNKNOWN
Platform: UNKNOWN
Classifier: Programming Language :: Python :: 3.6
Classifier: Programming Language :: Python :: 3.7
Classifier: Programming Language :: Python :: 3.8
Classifier: Programming Language :: Python :: 3.9
Classifier: License :: OSI Approved :: GNU Library or Lesser General Public License (LGPL)
Classifier: Operating System :: OS Independent
Requires-Python: >=3.6
Requires-Dist: requests
